create_prisma_app/__init__.py
create_prisma_app/cli.py
create_prisma_app-0.6.0.dist-info/METADATA
create_prisma_app-0.6.0.dist-info/WHEEL
create_prisma_app-0.6.0.dist-info/entry_points.txt
create_prisma_app-0.6.0.dist-info/top_level.txt
create_prisma_app-0.6.0.dist-info/RECORD
