Metadata-Version: 2.4
Name: create-prisma-app
Version: 0.6.0
Summary: A CLI tool to bootstrap Express + Prisma projects with PostgreSQL
Author-email: Sahil K Gupta <sahilkguptaprivate@gmail.com>
License-Expression: MIT
Requires-Python: >=3.8
